pyimporters_csv/__init__.py
pyimporters_csv/csv_parser.py
pyimporters_csv/excel.py
pyimporters_csv/text.py
pyimporters_csv-0.4.435.dist-info/entry_points.txt
pyimporters_csv-0.4.435.dist-info/WHEEL
pyimporters_csv-0.4.435.dist-info/METADATA
pyimporters_csv-0.4.435.dist-info/RECORD
